data_memory.v
`default_nettype none

module data_memory (
    input  wire        clk,
    input  wire        wen,       
    input  wire [31:0] addr,    
    input  wire [31:0] wdata,      
    output wire [31:0] rdata       
);

    reg [31:0] ram [0:63];

    always @(posedge clk) begin // Synchronous Write
        if (wen) begin
            ram[addr[7:2]] <= wdata;
        end
    end

    // Asynchronous Read: Constantly output the data at the requested address
    assign rdata = ram[addr[7:2]];

endmodule

alu.v
`default_nettype none /* This directive prevents implicit wire declarations, 
which can help catch typos and other mistakes in signal names. */

module alu (
    input  wire [31:0] a,
    input  wire [31:0] b,
    input  wire [3:0]  alu_ctrl,
    output reg  [31:0] result,
    output wire        zero
);

    assign zero = (result == 32'b0);

    always @(*) begin
        case (alu_ctrl)
            4'b0000: result = a + b;
            4'b0001: result = a - b;
            4'b0010: result = a & b;
            4'b0011: result = a | b;
            4'b0100: result = a ^ b;
            4'b0101: result = a << b[4:0]; 
            4'b0110: result = a >> b[4:0];
            4'b0111: result = $signed(a) >>> b[4:0]; // The arithmetic right shift (>>>) preserves the sign bit for signed numbers.
            4'b1000: result = $signed(a) < $signed(b); 
            4'b1001: result = a < b;
            default: result = 32'b0; 
        endcase
    end

endmodule

register_file.v
`default_nettype none

module register_file (
    input  wire        clk,      
    input  wire        wen, 
    
    // Read Port 1
    input  wire [4:0]  ra1, // Read Address 1 (Source 1)
    output wire [31:0] rd1, // Read Data 1
    
    // Read Port 2
    input  wire [4:0]  ra2,      
    output wire [31:0] rd2,     
    
    // Write Port
    input  wire [4:0]  wa,  // Write Address (Destination)
    input  wire [31:0] wd   // Write Data
);

    reg [31:0] mem [0:31];
    
    assign rd1 = (ra1 == 5'd0) ? 32'b0 : mem[ra1]; 
    assign rd2 = (ra2 == 5'd0) ? 32'b0 : mem[ra2]; 
    
    always @(posedge clk) begin
        if (wen && wa != 5'd0) begin
            mem[wa] <= wd;
        end
    end

endmodule

rv32i_core/control_unit.v
`default_nettype none

module control_unit (
    input  wire [6:0] opcode,     // Bottom 7 bits of instruction
    input  wire [2:0] funct3,     // 3-bit function code (used to determine specific instruction within a category)
    input  wire [6:0] funct7,     // 7-bit function code (used to distinguish ADD/SUB and SRL/SRA)
    
    output reg        wen,        // 1 = Write to Register File
    output reg        alu_src,    // 0 = Register (ra2), 1 = Immediate
    output reg        mem_write,  // 1 = Write to Data RAM
    output reg        result_src, // 0 = ALU Result, 1 = RAM Data
    output reg        branch,     // 1 = Branch instruction
    output reg [3:0]  alu_ctrl    // 4-bit command to the ALU
);

    // 1. MAIN DECODER: Routes data paths based on the instruction category (Opcode)
    always @(*) begin
        wen        = 0; 
        alu_src    = 0;
        mem_write  = 0; 
        result_src = 0;
        branch     = 0;
        
        case (opcode)
            7'b0110011: begin // R-TYPE: Math using two registers
                wen = 1; alu_src = 0; result_src = 0;
            end
            7'b0010011: begin // I-TYPE: Math using one register + an immediate value
                wen = 1; alu_src = 1; result_src = 0;
            end
            7'b0000011: begin // LOAD: Read from RAM, save into a register
                wen = 1; alu_src = 1; result_src = 1;
            end
            7'b0100011: begin // STORE: Write register data into RAM
                wen = 0; alu_src = 1; mem_write = 1;
            end
            7'b1100011: begin // BRANCH: Compare two registers, trigger PC jump
                wen = 0; alu_src = 0; branch = 1; 
            end
            default: ; 
        endcase
    end

    // 2. ALU DECODER: Determines exact math operation based on Opcode, funct3, and funct7
    always @(*) begin 
        alu_ctrl = 4'b0000; // Default to ADD (used for address calculations in LOAD/STORE and as a safe default)
        
        if (opcode == 7'b0110011) begin // R-Type 
            case (funct3)
                3'b000: alu_ctrl = (funct7[5]) ? 4'b0001 : 4'b0000; // SUB if funct7[5] is 1, else ADD
                3'b111: alu_ctrl = 4'b0010;                         // AND
                3'b110: alu_ctrl = 4'b0011;                         // OR
                3'b100: alu_ctrl = 4'b0100;                         // XOR
                3'b001: alu_ctrl = 4'b0101;                         // SLL (Shift Left Logical)
                3'b101: alu_ctrl = (funct7[5]) ? 4'b0111 : 4'b0110; // SRA if funct7[5] is 1, else SRL
                3'b010: alu_ctrl = 4'b1000;                         // SLT (Set Less Than Signed)
                3'b011: alu_ctrl = 4'b1001;                         // SLTU (Set Less Than Unsigned)
                default: alu_ctrl = 4'b0000;
            endcase
        end
        else if (opcode == 7'b0010011) begin // I-Type 
            case (funct3)
                3'b000: alu_ctrl = 4'b0000; // ADDI
                3'b111: alu_ctrl = 4'b0010; // ANDI
                3'b110: alu_ctrl = 4'b0011; // ORI
                3'b100: alu_ctrl = 4'b0100; // XORI
                default: alu_ctrl = 4'b0000;
            endcase
        end
        else if (opcode == 7'b1100011) begin // Branch Instructions
            alu_ctrl = 4'b0001; // Force ALU to SUBTRACT to check if rs1 == rs2 (Zero flag)
        end
    end

endmodule

rv32i_core/instruction_memory.v
`default_nettype none

module instruction_memory (
    input  wire [31:0] pc,
    output wire [31:0] instruction
);

    reg [31:0] rom [0:63];

    initial begin
        $readmemh("program.hex", rom); // Load instructions from a hex file. Each line corresponds to one instruction.
    end

    // pc[7:2] divides the address by 4 to access the correct array index.
    assign instruction = rom[pc[7:2]];

endmodule

program_counter.v
`default_nettype none

module program_counter (
    input  wire        clk,
    input  wire        reset,
    input  wire [31:0] pc_next,
    output reg  [31:0] pc
);

    always @(posedge clk or posedge reset) begin
        if (reset) begin
            pc <= 32'b0;
        end else begin
            pc <= pc_next;
        end
    end

endmodule

rv32i_core/rv32i_core.v
`default_nettype none

module rv32i_core (
    input wire clk,
    input wire reset
);

    // Internal Wires 
    wire [31:0] pc, pc_next, pc_plus4, instr;
    wire [31:0] rd1, rd2, wd, alu_result, read_data, imm_ext;
    wire [3:0]  alu_ctrl;
    wire        wen, alu_src, mem_write, result_src, branch, alu_zero;

    // Program Counter Logic 
    assign pc_plus4 = pc + 4;
    assign pc_next = (branch && alu_zero) ? (pc + imm_ext) : pc_plus4;

    program_counter pc_inst (
        .clk(clk),
        .reset(reset),
        .pc_next(pc_next),
        .pc(pc)
    );

    // Instruction Fetch 
    instruction_memory imem_inst (
        .pc(pc),
        .instruction(instr)
    );

    // Control Unit 
    control_unit cu_inst (
        .opcode(instr[6:0]),
        .funct3(instr[14:12]),
        .funct7(instr[31:25]),
        .wen(wen),
        .alu_src(alu_src),
        .mem_write(mem_write),
        .result_src(result_src),
        .branch(branch),
        .alu_ctrl(alu_ctrl)
    );

    // Register File
    assign wd = (result_src) ? read_data : alu_result;

    register_file rf_inst (
        .clk(clk),
        .wen(wen),
        .ra1(instr[19:15]),
        .ra2(instr[24:20]),
        .wa(instr[11:7]),
        .wd(wd),
        .rd1(rd1),
        .rd2(rd2)
    );

    // Immediate Generation (Sign Extension) 
    assign imm_ext = {{20{instr[31]}}, instr[31:20]}; 

    // ALU 
    wire [31:0] alu_input_b = (alu_src) ? imm_ext : rd2;

    alu alu_inst (
        .a(rd1),
        .b(alu_input_b),
        .alu_ctrl(alu_ctrl),
        .result(alu_result),
        .zero(alu_zero)
    );

    // Data Memory 
    data_memory dmem_inst (
        .clk(clk),
        .wen(mem_write),
        .addr(alu_result),
        .wdata(rd2),
        .rdata(read_data)
    );

endmodule

tb_top.v
`default_nettype none
`timescale 1ns/1ps

module tb_top;
    reg clk;
    reg reset;

    rv32i_core uut (
        .clk(clk),
        .reset(reset)
    );

    initial begin
        clk = 0;
        forever #5 clk = ~clk;
    end

    initial begin
        $dumpfile("cpu_test.vcd");
        $dumpvars(0, tb_top);
        
        // Reset the system
        reset = 1; #15;
        reset = 0;

        // Run for 100ns (enough for several instructions)
        #100;
        $finish;
    end
endmodule

cpu_test.vcd
$date
	Tue Mar 31 18:37:29 2026
$end
$version
	Icarus Verilog
$end
$timescale
	1ps
$end
$scope module tb_top $end
$var reg 1 ! clk $end
$var reg 1 " reset $end
$scope module uut $end
$var wire 1 ! clk $end
$var wire 1 " reset $end
$var wire 1 # wen $end
$var wire 32 $ wd [31:0] $end
$var wire 1 % result_src $end
$var wire 32 & read_data [31:0] $end
$var wire 32 ' rd2 [31:0] $end
$var wire 32 ( rd1 [31:0] $end
$var wire 32 ) pc_plus4 [31:0] $end
$var wire 32 * pc_next [31:0] $end
$var wire 32 + pc [31:0] $end
$var wire 1 , mem_write $end
$var wire 32 - instr [31:0] $end
$var wire 32 . imm_ext [31:0] $end
$var wire 1 / branch $end
$var wire 1 0 alu_zero $end
$var wire 1 1 alu_src $end
$var wire 32 2 alu_result [31:0] $end
$var wire 32 3 alu_input_b [31:0] $end
$var wire 4 4 alu_ctrl [3:0] $end
$scope module alu_inst $end
$var wire 32 5 b [31:0] $end
$var wire 1 0 zero $end
$var wire 4 6 alu_ctrl [3:0] $end
$var wire 32 7 a [31:0] $end
$var reg 32 8 result [31:0] $end
$upscope $end
$scope module cu_inst $end
$var wire 3 9 funct3 [2:0] $end
$var wire 7 : funct7 [6:0] $end
$var wire 7 ; opcode [6:0] $end
$var reg 4 < alu_ctrl [3:0] $end
$var reg 1 1 alu_src $end
$var reg 1 / branch $end
$var reg 1 , mem_write $end
$var reg 1 % result_src $end
$var reg 1 # wen $end
$upscope $end
$scope module dmem_inst $end
$var wire 32 = addr [31:0] $end
$var wire 1 ! clk $end
$var wire 32 > rdata [31:0] $end
$var wire 1 , wen $end
$var wire 32 ? wdata [31:0] $end
$upscope $end
$scope module imem_inst $end
$var wire 32 @ instruction [31:0] $end
$var wire 32 A pc [31:0] $end
$upscope $end
$scope module pc_inst $end
$var wire 1 ! clk $end
$var wire 32 B pc_next [31:0] $end
$var wire 1 " reset $end
$var reg 32 C pc [31:0] $end
$upscope $end
$scope module rf_inst $end
$var wire 1 ! clk $end
$var wire 5 D ra1 [4:0] $end
$var wire 5 E ra2 [4:0] $end
$var wire 5 F wa [4:0] $end
$var wire 32 G wd [31:0] $end
$var wire 1 # wen $end
$var wire 32 H rd2 [31:0] $end
$var wire 32 I rd1 [31:0] $end
$upscope $end
$upscope $end
$upscope $end
$enddefinitions $end
$comment Show the parameter values. $end
$dumpall
$end
#0
$dumpvars
b0 I
bx H
b1010 G
b1 F
b1010 E
b0 D
b0 C
b100 B
b0 A
b101000000000000010010011 @
bx ?
bx >
b1010 =
b0 <
b10011 ;
b0 :
b0 9
b1010 8
b0 7
b0 6
b1010 5
b0 4
b1010 3
b1010 2
11
00
0/
b1010 .
b101000000000000010010011 -
0,
b0 +
b100 *
b100 )
b0 (
bx '
bx &
0%
b1010 $
1#
1"
0!
$end
#5000
1!
#10000
0!
#15000
b10100 $
b10100 G
b10100 2
b10100 8
b10100 =
b10100 3
b10100 5
b10100 .
b10 F
b10100 E
b1010000000000000100010011 -
b1010000000000000100010011 @
b1000 *
b1000 B
b1000 )
b100 +
b100 A
b100 C
1!
0"
#20000
0!
#25000
b11110 $
b11110 G
b11110 2
b11110 8
b11110 =
b10100 '
b10100 ?
b10100 H
b1010 (
b1010 7
b1010 I
01
1#
b10 .
b11 F
b10 E
b1 D
b110011 ;
b1000001000000110110011 -
b1000001000000110110011 @
b1100 *
b1100 B
b1100 )
b1000 +
b1000 A
b1000 C
1!
#30000
0!
#35000
b1010 $
b1010 G
b1010 3
b1010 5
00
b1010 2
b1010 8
b1010 =
b1010 '
b1010 ?
b1010 H
b10100 (
b10100 7
b10100 I
b1 4
b1 6
b1 <
b10000000001 .
b100 F
b1 E
b10 D
b100000 :
b1000000000100010000001000110011 -
b1000000000100010000001000110011 @
b10000 *
b10000 B
b10000 )
b1100 +
b1100 A
b1100 C
1!
#40000
0!
#45000
b0 $
b0 G
10
b0 2
b0 8
b0 =
b10100 3
b10100 5
b10100 '
b10100 ?
b10100 H
b1010 (
b1010 7
b1010 I
b10 4
b10 6
b10 <
b10 .
b101 F
b10 E
b1 D
b0 :
b111 9
b1000001111001010110011 -
b1000001111001010110011 @
b10100 *
b10100 B
b10100 )
b10000 +
b10000 A
b10000 C
1!
#50000
0!
#55000
b11110 $
b11110 G
00
b11110 2
b11110 8
b11110 =
b11 4
b11 6
b11 <
b110 F
b110 9
b1000001110001100110011 -
b1000001110001100110011 @
b11000 *
b11000 B
b11000 )
b10100 +
b10100 A
b10100 C
1!
#60000
0!
#65000
b11 $
b11 G
b11 2
b11 8
b11 =
b11 3
b11 5
b11110 '
b11110 ?
b11110 H
b0 (
b0 7
b0 I
b0 4
b0 6
b0 <
1,
11
0#
b11 .
b100 F
b11 E
b0 D
b10 9
b100011 ;
b1100000010001000100011 -
b1100000010001000100011 @
b11100 *
b11100 B
b11100 )
b11000 +
b11000 A
b11000 C
1!
#70000
0!
#75000
b100 2
b100 8
b100 =
bx $
bx G
b100 3
b100 5
b1010 '
b1010 ?
b1010 H
1%
1#
0,
11
b100 .
b111 F
b100 E
b11 ;
b10000000010001110000011 -
b10000000010001110000011 @
b100000 *
b100000 B
bx &
bx >
b100000 )
b11100 +
b11100 A
b11100 C
1!
#80000
0!
#85000
b11110 &
b11110 >
10
b0 2
b0 8
b0 =
b0 $
b0 G
b1010 3
b1010 5
b1010 (
b1010 7
b1010 I
b1 4
b1 6
b1 <
1/
0%
01
0#
b1000 F
b1 D
b0 9
b1100011 ;
b10000001000010001100011 -
b10000001000010001100011 @
b100100 *
b100100 B
b100100 )
b100000 +
b100000 A
b100000 C
1!
#90000
0!
#95000
bx &
bx >
b1100011 $
b1100011 G
00
b1100011 2
b1100011 8
b1100011 =
b1100011 3
b1100011 5
b11110 '
b11110 ?
b11110 H
b0 (
b0 7
b0 I
b0 4
b0 6
b0 <
11
1#
0/
b1100011 .
b11 E
b0 D
b11 :
b10011 ;
b110001100000000010000010011 -
b110001100000000010000010011 @
b101000 *
b101000 B
b101000 )
b100100 +
b100100 A
b100100 C
1!
#100000
0!
#105000
b1100100 $
b1100100 G
b1100100 2
b1100100 8
b1100100 =
b1100100 3
b1100100 5
b1010 '
b1010 ?
b1010 H
b1100100 .
b1001 F
b100 E
b110010000000000010010010011 -
b110010000000000010010010011 @
b101100 *
b101100 B
b101100 )
b101000 +
b101000 A
b101000 C
1!
#110000
0!
#115000
b11110 &
b11110 >
b0 $
b0 G
10
b0 2
b0 8
b0 =
b0 3
b0 5
b0 '
b0 ?
b0 H
b1 4
b1 6
b1 <
1/
01
0#
b0 .
b0 F
b0 E
b0 :
b1100011 ;
b1100011 -
b1100011 @
b101100 *
b101100 B
b110000 )
b101100 +
b101100 A
b101100 C
1!
